[{"Name":"Python","Bytes":11574819,"CodeBytes":0,"Lines":284805,"Code":216029,"Comment":38857,"Blank":29919,"Complexity":22167,"Count":922,"WeightedComplexity":0,"Files":[],"LineLength":null,"ULOC":0},{"Name":"JSON","Bytes":21599826,"CodeBytes":0,"Lines":542910,"Code":542909,"Comment":0,"Blank":1,"Complexity":0,"Count":814,"WeightedComplexity":0,"Files":[],"LineLength":null,"ULOC":0},{"Name":"YAML","Bytes":828363,"CodeBytes":0,"Lines":25225,"Code":23269,"Comment":1086,"Blank":870,"Complexity":0,"Count":324,"WeightedComplexity":0,"Files":[],"LineLength":null,"ULOC":0},{"Name":"Shell","Bytes":323049,"CodeBytes":0,"Lines":10952,"Code":8815,"Comment":818,"Blank":1319,"Complexity":545,"Count":131,"WeightedComplexity":0,"Files":[],"LineLength":null,"ULOC":0},{"Name":"Markdown","Bytes":406056,"CodeBytes":0,"Lines":9261,"Code":6924,"Comment":0,"Blank":2337,"Complexity":0,"Count":103,"WeightedComplexity":0,"Files":[],"LineLength":null,"ULOC":0},{"Name":"Dockerfile","Bytes":5205,"CodeBytes":0,"Lines":151,"Code":109,"Comment":23,"Blank":19,"Complexity":24,"Count":4,"WeightedComplexity":0,"Files":[],"LineLength":null,"ULOC":0},{"Name":"Plain Text","Bytes":183,"CodeBytes":0,"Lines":10,"Code":10,"Comment":0,"Blank":0,"Complexity":0,"Count":3,"WeightedComplexity":0,"Files":[],"LineLength":null,"ULOC":0},{"Name":"TOML","Bytes":10704,"CodeBytes":0,"Lines":355,"Code":304,"Comment":19,"Blank":32,"Complexity":7,"Count":2,"WeightedComplexity":0,"Files":[],"LineLength":null,"ULOC":0},{"Name":"Autoconf","Bytes":165,"CodeBytes":0,"Lines":5,"Code":5,"Comment":0,"Blank":0,"Complexity":0,"Count":1,"WeightedComplexity":0,"Files":[],"LineLength":null,"ULOC":0},{"Name":"C++","Bytes":29803,"CodeBytes":0,"Lines":849,"Code":629,"Comment":124,"Blank":96,"Complexity":99,"Count":1,"WeightedComplexity":0,"Files":[],"LineLength":null,"ULOC":0},{"Name":"Cuda","Bytes":4420,"CodeBytes":0,"Lines":110,"Code":63,"Comment":30,"Blank":17,"Complexity":12,"Count":1,"WeightedComplexity":0,"Files":[],"LineLength":null,"ULOC":0},{"Name":"JSONL","Bytes":481,"CodeBytes":0,"Lines":2,"Code":2,"Comment":0,"Blank":0,"Complexity":0,"Count":1,"WeightedComplexity":0,"Files":[],"LineLength":null,"ULOC":0},{"Name":"License","Bytes":17640,"CodeBytes":0,"Lines":327,"Code":270,"Comment":0,"Blank":57,"Complexity":0,"Count":1,"WeightedComplexity":0,"Files":[],"LineLength":null,"ULOC":0},{"Name":"Makefile","Bytes":313,"CodeBytes":0,"Lines":13,"Code":9,"Comment":0,"Blank":4,"Complexity":0,"Count":1,"WeightedComplexity":0,"Files":[],"LineLength":null,"ULOC":0},{"Name":"Patch","Bytes":540,"CodeBytes":0,"Lines":13,"Code":13,"Comment":0,"Blank":0,"Complexity":0,"Count":1,"WeightedComplexity":0,"Files":[],"LineLength":null,"ULOC":0}]